README.rst
setup.py
fastidious/__init__.py
fastidious/bootstrap.py
fastidious/expressions.py
fastidious/parser.py
fastidious/tools.py
fastidious.egg-info/.SOURCES.txt.swp
fastidious.egg-info/PKG-INFO
fastidious.egg-info/SOURCES.txt
fastidious.egg-info/dependency_links.txt
fastidious.egg-info/requires.txt
fastidious.egg-info/top_level.txt
fastidious/contrib/__init__.py