Metadata-Version: 1.1
Name: fastidious
Version: 0.1.dev0
Summary: Yet another python parser generator
Home-page: https://github.com/lisael/fastidious
Author: lisael
Author-email: lisael@lisael.org
License: GPLv3
Keywords: PEG parser generator lexer
Platform: UNKNOWN
Classifier: Development Status :: 3 - Alpha
Classifier: Intended Audience :: Developers
Classifier: Topic :: Software Development :: Code Generators
Classifier: Topic :: Software Development :: Compilers
Classifier: License :: OSI Approved :: GNU General Public License v3 (GPLv3)
Classifier: Programming Language :: Python :: 2
Classifier: Programming Language :: Python :: 2.7
